python_hosts/__init__.py
python_hosts/exception.py
python_hosts/hosts.py
python_hosts/unicode_utils.py
python_hosts/utils.py
python_hosts-1.1.2.dist-info/LICENSE.txt
python_hosts-1.1.2.dist-info/METADATA
python_hosts-1.1.2.dist-info/WHEEL
python_hosts-1.1.2.dist-info/top_level.txt
python_hosts-1.1.2.dist-info/RECORD
